CHANGES.txt
README.txt
bootstrap.py
buildout.cfg
setup.py
src/ks/__init__.py
src/ks.pager.egg-info/PKG-INFO
src/ks.pager.egg-info/SOURCES.txt
src/ks.pager.egg-info/dependency_links.txt
src/ks.pager.egg-info/namespace_packages.txt
src/ks.pager.egg-info/not-zip-safe
src/ks.pager.egg-info/requires.txt
src/ks.pager.egg-info/top_level.txt
src/ks/pager/README.txt
src/ks/pager/__init__.py
src/ks/pager/configure.zcml
src/ks/pager/interfaces.py
src/ks/pager/demo/__init__.py
src/ks/pager/demo/configure.zcml
src/ks/pager/demo/browser/__init__.py
src/ks/pager/demo/browser/configure.zcml
src/ks/pager/demo/browser/demo.pt
src/ks/pager/demo/etc/ks.pager.demo-configure.zcml
src/ks/pager/etc/ks.pager-configure.zcml
src/ks/pager/listing/__init__.py
src/ks/pager/listing/configure.zcml
src/ks/pager/listing/listing.pt
src/ks/pager/listing/listing_base.pt
src/ks/pager/listing/pager_base.pt
src/ks/pager/listing/statistics_base.pt
src/ks/pager/locales/ks.pager.pot
src/ks/pager/locales/en/LC_MESSAGES/ks.pager.po
src/ks/pager/locales/ru/LC_MESSAGES/ks.pager.mo
src/ks/pager/locales/ru/LC_MESSAGES/ks.pager.po
src/ks/pager/pagedsourceadapter/__init__.py
src/ks/pager/pagedsourceadapter/configure.zcml
src/ks/pager/pagedsourceadapter/pagedsourceadapter.py
src/ks/pager/pageradapter/__init__.py
src/ks/pager/pageradapter/configure.zcml
src/ks/pager/pageradapter/pageradapter.py
src/ks/pager/pagerfactoryadapter/__init__.py
src/ks/pager/pagerfactoryadapter/configure.zcml
src/ks/pager/pagerfactoryadapter/pagerfactoryadapter.py
src/ks/pager/pagerparamsadapter/__init__.py
src/ks/pager/pagerparamsadapter/configure.zcml
src/ks/pager/pagerparamsadapter/pagerparamsadapter.py
