Metadata-Version: 1.0
Name: ks.pager
Version: 1.0.1
Summary: Easy get paged listings of objects with ks.formkeeper for Hivurt
Home-page: http://code.keysolutions.ru/ks.pager
Author: Key Solutions Development TEAM
Author-email: ksd-team@keysolutions.ru
License: ZPL 2.1
Platform: UNKNOWN
Classifier: Intended Audience :: Developers
Classifier: License :: OSI Approved :: Zope Public License
Classifier: Programming Language :: Python
Classifier: Natural Language :: English
Classifier: Operating System :: OS Independent
Classifier: Topic :: Internet :: WWW/HTTP
Classifier: Topic :: Software Development
Classifier: Framework :: Zope3
